bytedance_creative_open_core/__init__.py
bytedance_creative_open_core-0.0.1.dist-info/METADATA
bytedance_creative_open_core-0.0.1.dist-info/WHEEL
bytedance_creative_open_core-0.0.1.dist-info/top_level.txt
bytedance_creative_open_core-0.0.1.dist-info/RECORD
