Metadata-Version: 2.1
Name: bytedance-creative-open-core
Version: 0.0.1
Summary: A simple package named bytedance_creative_open_core
Home-page: https://github.com/artifact/bytedance_creative_open_core.git
Author: artifact
Author-email: artifact@example.com
License: UNKNOWN
Platform: UNKNOWN
Classifier: Programming Language :: Python :: 3
Classifier: License :: OSI Approved :: MIT License
Classifier: Operating System :: OS Independent
